bagmanager/__init__.py
bagmanager-0.0.5.dist-info/LICENSE
bagmanager-0.0.5.dist-info/METADATA
bagmanager-0.0.5.dist-info/WHEEL
bagmanager-0.0.5.dist-info/top_level.txt
bagmanager-0.0.5.dist-info/RECORD
