Metadata-Version: 2.1
Name: bagmanager
Version: 0.0.5
Summary: A thin wrapper around rosbag.Bag with some convenient methods
Home-page: https://github.com/omrirz/bagmanager.git
Author: Omri Rozenzaft
Author-email: omrirz@gmail.com
License: UNKNOWN
Platform: UNKNOWN
Classifier: Programming Language :: Python
Classifier: Programming Language :: Python :: 3.6
Classifier: Programming Language :: Python :: 3.7
Classifier: Programming Language :: Python :: 3.8
Classifier: Programming Language :: Python :: 3 :: Only
Classifier: License :: OSI Approved :: MIT License
Classifier: Operating System :: Unix
Requires-Python: >=3.6
Requires-Dist: numpy
Requires-Dist: pyyaml
Requires-Dist: pyrosenv
Requires-Dist: pycrypto
Requires-Dist: gnupg
